{"title":"블로터 ─ 비즈니스 ─ 헤드라인","url":"https://www.bloter.net/section?id=sectionBusiness2","favicon":"https://www.bloter.net/favicon.png","elements":[{"title":"'이대남' 표심에 권좌가 있다…이재명·윤석열 가상자산 공약 격돌","contents":"<span class=\"writer\">강승혁</span>                        <span class=\"date\">2022-01-19 19:01:05</span>","link":"https://www.bloter.net/newsView/blt202201190069","retrieved":1642587452878,"image":"https://www.bloter.net/data/blt/image/2022/01/19/blt202201190036.570x320.0.jpg"},{"title":"가상자산은 범죄에 취약하다? 통념 깨는 미국 국방정책","contents":"<span class=\"writer\">강승혁</span>                        <span class=\"date\"></span>","link":"https://www.bloter.net/newsView/blt202201030101","retrieved":1642587452880},{"title":"메타 자회사 '왓츠앱', 암호화폐 주고받기 기능 추가","contents":"<span class=\"writer\">황금빛</span>                        <span class=\"date\"></span>","link":"https://www.bloter.net/newsView/blt202112100005","retrieved":1642587452882},{"title":"토스가 가상자산 시장 바라만 볼까?","contents":"<span class=\"writer\">강승혁</span>                        <span class=\"date\"></span>","link":"https://www.bloter.net/newsView/blt202110250072","retrieved":1642587452883},{"title":"국가 암호화폐가 온다..비트·알트 살아남을 수 있나","contents":"<span class=\"writer\">이일호</span>                        <span class=\"date\"></span>","link":"https://www.bloter.net/newsView/blt202106120002","retrieved":1642587452884}]}