{"title":"블로터 ─ 비즈니스 ─ 헤드라인","url":"https://www.bloter.net/section?id=sectionBusiness2","favicon":"https://www.bloter.net/favicon.png","elements":[{"title":"효성첨단소재, 언양공장 매각 불발...1년치 CAPEX 비용 마련 숙제","contents":"<span class=\"writer\">김성진</span>                        <span class=\"date\">2022-12-20 13:23:44</span>","link":"https://www.bloter.net/newsView/blt202212200005","retrieved":1671513231169,"image":"https://www.bloter.net/data/blt/image/2022/12/20/blt202212200007.570x320.0.png"},{"title":"효성그룹, 전지소재 사업 진출...전구체·폐배터리 재활용 분야","contents":"<span class=\"writer\">구태우</span>                        <span class=\"date\"></span>","link":"https://www.bloter.net/newsView/blt202211110016","retrieved":1671513231181},{"title":"효성화학 베트남 투자 재무부담 현실로...'관건은 수율'","contents":"<span class=\"writer\">구태우</span>                        <span class=\"date\"></span>","link":"https://www.bloter.net/newsView/blt202210160005","retrieved":1671513231189},{"title":"구멍난 단통법? \"벌점제 실효성 없다\"…뿔난 휴대폰 유통점들","contents":"<span class=\"writer\">이건한</span>                        <span class=\"date\"></span>","link":"https://www.bloter.net/newsView/blt202204260061","retrieved":1671513231192},{"title":"구글·애플의 '탄소중립' 점수는...독일 NCI \"실효성 미미\"","contents":"<span class=\"writer\">최경미</span>                        <span class=\"date\"></span>","link":"https://www.bloter.net/newsView/blt202202110324","retrieved":1671513231192}]}