{"title":"블로터 ─ 비즈니스","url":"https://www.bloter.net/section?id=sectionBusiness2","favicon":"https://www.bloter.net/favicon.png","elements":[{"title":"포스코 사상최대 실적...PER 저평가 '역대급', 현대제철·KG동부제철보다 낮다","contents":"<span class=\"writer\">구태우</span>                        <span class=\"date\">2022-01-13 16:49:17</span>","link":"https://www.bloter.net/newsView/blt202201130034","retrieved":1642141291351,"image":"https://www.bloter.net/data/blt/image/2022/01/13/blt202201130014.407x229.0.jpg"},{"title":"네이버파이낸셜 떠나는 최인혁...차기 대표는 ‘재무통’ 박상진 CFO","contents":"<span class=\"writer\">황금빛</span>                        <span class=\"date\">2022-01-13 14:46:34</span>","link":"https://www.bloter.net/newsView/blt202201130033","retrieved":1642134076385,"image":"https://www.bloter.net/data/blt/image/2022/01/13/blt202201130010.407x229.0.png"},{"title":"'리멤버'가 1600억원으로 하려는 것...비즈니스 포털?","contents":"<span class=\"writer\">황금빛</span>                        <span class=\"date\">2022-01-13 13:16:09</span>","link":"https://www.bloter.net/newsView/blt202201120024","retrieved":1642121759436,"image":"https://www.bloter.net/data/blt/image/2022/01/12/blt202201120019.407x229.0.jpg"},{"title":"소니, PS4 생산 계속하지만…\"정작 구매할 길이 없다\"","contents":"<span class=\"writer\">최경미</span>                        <span class=\"date\">2022-01-13 10:54:18</span>","link":"https://www.bloter.net/newsView/blt202201130017","retrieved":1642121759438,"image":"https://www.bloter.net/data/blt/image/2022/01/13/blt202201130004.407x229.0.png"},{"title":"인도 틱톡 금지 반사효과?… 인스타그램, 글로벌 다운로드 1위 탈환","contents":"<span class=\"writer\">최경미</span>                        <span class=\"date\">2022-01-13 09:56:40</span>","link":"https://www.bloter.net/newsView/blt202201130008","retrieved":1642062142483,"image":"https://www.bloter.net/data/blt/image/2022/01/13/blt202201130002.407x229.0.jpg"},{"title":"트위터 떠난 잭 도시, 소송 직면한 비트코인 개발자 지원 펀드 제안","contents":"<span class=\"writer\">최경미</span>                        <span class=\"date\">2022-01-13 08:52:13</span>","link":"https://www.bloter.net/newsView/blt202201130001","retrieved":1642054829118,"image":"https://www.bloter.net/data/blt/image/2022/01/13/blt202201130001.407x229.0.jpg"}]}