{"title":"블로터 ─ 비즈니스 ─ 헤드라인","url":"https://www.bloter.net/section?id=sectionBusiness2","favicon":"https://www.bloter.net/favicon.png","elements":[{"title":"SK온, 전기차 1대당 10개 들어가는 '배터리 칩' 자체 개발","contents":"<span class=\"writer\">김성진</span>                        <span class=\"date\">2022-04-04 10:48:51</span>","link":"https://www.bloter.net/newsView/blt202204040015","retrieved":1649041405639,"image":"https://www.bloter.net/data/blt/image/2022/04/04/blt202204040007.570x320.0.jpg"},{"title":"SK온 '규모의 경제' 달성 가능할까...실적·재무·현금흐름 '3박자 악화'","contents":"<span class=\"writer\">구태우</span>                        <span class=\"date\"></span>","link":"https://www.bloter.net/newsView/blt202203210188","retrieved":1649041405640},{"title":"SK온, IPO 천천히 해도 괜찮은 이유","contents":"<span class=\"writer\">김성진</span>                        <span class=\"date\"></span>","link":"https://www.bloter.net/newsView/blt202201300003","retrieved":1649041405642},{"title":"SK온, 배터리 생산부터 서비스까지...'생애주기 책임진다'","contents":"<span class=\"writer\">김성진</span>                        <span class=\"date\"></span>","link":"https://www.bloter.net/newsView/blt202111270004","retrieved":1649041405643},{"title":"국내 전지3사 '3Q 누적 성적표'...매출 성장은 SK온, 영업익은 삼성SDI 우수","contents":"<span class=\"writer\">구태우</span>                        <span class=\"date\"></span>","link":"https://www.bloter.net/newsView/blt202111070001","retrieved":1649041405644}]}