{"title":"블로터 ─ 비즈니스","url":"https://www.bloter.net/section?id=sectionBusiness2","favicon":"https://www.bloter.net/favicon.png","elements":[{"title":"박철완 vs 금호석유화학, 경영권 분쟁으로 보는 소액주주 손익계산서","contents":"<span class=\"writer\">문병선</span>                        <span class=\"date\">2022-03-16 08:00:03</span>","link":"https://www.bloter.net/newsView/blt202203150199","retrieved":1647392813307,"image":"https://www.bloter.net/data/blt/image/2022/03/15/blt202203150025.407x229.0.png"},{"title":"'재무통' 박상진 네이버파이낸셜 대표 선임…카드사·토스 공세 막을까","contents":"<span class=\"writer\">강승혁</span>                        <span class=\"date\">2022-03-15 16:33:30</span>","link":"https://www.bloter.net/newsView/blt202203150045","retrieved":1647392813310,"image":"https://www.bloter.net/data/blt/image/2022/03/15/blt202203150009.407x229.0.jpg"},{"title":"포스코홀딩스 임원비율 13.5%...LG보다 높고, GS·롯데보다 낮아","contents":"<span class=\"writer\">구태우</span>                        <span class=\"date\">2022-03-15 15:18:06</span>","link":"https://www.bloter.net/newsView/blt202203150015","retrieved":1647392813313,"image":"https://www.bloter.net/data/blt/image/2022/03/15/blt202203150017.407x229.0.jpg"},{"title":"주총 앞둔 삼성전자 경영진, 연이은 자사주 매입","contents":"<span class=\"writer\">최창원</span>                        <span class=\"date\">2022-03-15 14:56:32</span>","link":"https://www.bloter.net/newsView/blt202203150060","retrieved":1647392813314,"image":"https://www.bloter.net/data/blt/image/2022/03/15/blt202203150016.407x229.0.png"},{"title":"폭스콘, 중국 내 코로나19 확산에 아이폰 공장 가동 멈췄다","contents":"<span class=\"writer\">최경미</span>                        <span class=\"date\">2022-03-15 10:01:31</span>","link":"https://www.bloter.net/newsView/blt202203150005","retrieved":1647392813319,"image":"https://www.bloter.net/data/blt/image/2022/03/15/blt202203150003.407x229.0.jpeg"},{"title":"러시아 “ISS 미 우주비행사, 예정대로 지구 귀환할 것”","contents":"<span class=\"writer\">최경미</span>                        <span class=\"date\">2022-03-15 09:23:28</span>","link":"https://www.bloter.net/newsView/blt202203150002","retrieved":1647335872935,"image":"https://www.bloter.net/data/blt/image/2022/03/15/blt202203150002.407x229.0.jpeg"}]}