{"title":"블로터 ─ 비즈니스 ─ 헤드라인","url":"https://www.bloter.net/section?id=sectionBusiness2","favicon":"https://www.bloter.net/favicon.png","elements":[{"title":"우크라이나 침공이 미국과 러시아의 ‘우주협력’에 미치는 영향","contents":"<span class=\"writer\">최경미</span>                        <span class=\"date\">2022-02-26 09:00:02</span>","link":"https://www.bloter.net/newsView/blt202202250288","retrieved":1645836897238,"image":"https://www.bloter.net/data/blt/image/2022/02/25/blt202202250064.570x320.0.jpeg"},{"title":"양향자 의원 “러시아 우크라 침공 규탄…반도체 수출 제재 동참해야”","contents":"<span class=\"writer\">정두용</span>                        <span class=\"date\"></span>","link":"https://www.bloter.net/newsView/blt202202250066","retrieved":1645836897238},{"title":"러시아 ‘우크라 침공’…테크 기업도 대응","contents":"<span class=\"writer\">최경미</span>                        <span class=\"date\"></span>","link":"https://www.bloter.net/newsView/blt202202250005","retrieved":1645836897242},{"title":"트위터, 우크라이나 사태  영상 공유한 일부 계정 정지...\"실수였다\"","contents":"<span class=\"writer\">최경미</span>                        <span class=\"date\"></span>","link":"https://www.bloter.net/newsView/blt202202240003","retrieved":1645836897247},{"title":"러 인공위성 요격에 ISS 우주비행사 '대피'...우주 쓰레기 몸살 심해진다","contents":"<span class=\"writer\">이건한</span>                        <span class=\"date\"></span>","link":"https://www.bloter.net/newsView/blt202111170016","retrieved":1645836897258}]}