{"title":"블로터 ─ 비즈니스 ─ 헤드라인","url":"https://www.bloter.net/section?id=sectionBusiness2","favicon":"https://www.bloter.net/favicon.png","elements":[{"title":"암호화폐 대출 업체 ‘블록파이’, 미 증권당국에 1억달러 벌금 지급 합의","contents":"<span class=\"writer\">최경미</span>                        <span class=\"date\">2022-02-15 09:42:23</span>","link":"https://www.bloter.net/newsView/blt202202150008","retrieved":1644886895243,"image":"https://www.bloter.net/data/blt/image/2022/02/15/blt202202150002.570x320.0.png"},{"title":"구글클라우드, 암호화폐 채굴 위협도 탐지한다","contents":"<span class=\"writer\">김인경</span>                        <span class=\"date\"></span>","link":"https://www.bloter.net/newsView/blt202202140147","retrieved":1644886895247},{"title":"미 규제당국, 블록체인 기반 증권거래소 최초 승인","contents":"<span class=\"writer\">최경미</span>                        <span class=\"date\"></span>","link":"https://www.bloter.net/newsView/blt202201310001","retrieved":1644886895249},{"title":"케이뱅크, 비이자이익 대폭 개선…'암호화폐' 효과 톡톡","contents":"<span class=\"writer\">박유진</span>                        <span class=\"date\"></span>","link":"https://www.bloter.net/newsView/blt202106010015","retrieved":1644886895251},{"title":"1분기 전세계 암호화폐 시장에 45억달러 유입","contents":"<span class=\"writer\">박현준</span>                        <span class=\"date\"></span>","link":"https://www.bloter.net/newsView/blt202104070004","retrieved":1644886895274}]}