{"title":"블로터 ─ 비즈니스","url":"https://www.bloter.net/section?id=sectionBusiness2","favicon":"https://www.bloter.net/favicon.png","elements":[{"title":"DB의 지주전환…DB하이텍 잘 품는 방법은?","contents":"<span class=\"writer\">이일호</span>                        <span class=\"date\">2022-05-03 12:00:02</span>","link":"https://www.bloter.net/newsView/blt202205030040","retrieved":1651562220513,"image":"https://www.bloter.net/data/blt/image/2022/05/03/blt202205030019.407x229.0.jpg"},{"title":"현대무벡스, 2차전지 물류 솔루션 시장 진출...그룹 재건의 '밀알'될까","contents":"<span class=\"writer\">구태우</span>                        <span class=\"date\">2022-05-03 11:44:29</span>","link":"https://www.bloter.net/newsView/blt202205030016","retrieved":1651562220515,"image":"https://www.bloter.net/data/blt/image/2022/05/03/blt202205030014.407x229.0.jpg"},{"title":"인사부터 TF 신설까지...삼성전자, M&A 속도 내나","contents":"<span class=\"writer\">최창원</span>                        <span class=\"date\">2022-05-03 10:46:53</span>","link":"https://www.bloter.net/newsView/blt202205030025","retrieved":1651558869332,"image":"https://www.bloter.net/data/blt/image/2022/05/03/blt202205030011.407x229.0.jpg"},{"title":"메타, 차세대 AR·VR 헤드셋 출시하나…“9월 공개 예정”","contents":"<span class=\"writer\">최경미</span>                        <span class=\"date\">2022-05-03 09:30:29</span>","link":"https://www.bloter.net/newsView/blt202205030009","retrieved":1651555195983,"image":"https://www.bloter.net/data/blt/image/2022/05/03/blt202205030002.407x229.0.jpeg"},{"title":"아마존, 두 번째 노조 결성 무산…사측 ‘방해 공작’ 의혹","contents":"<span class=\"writer\">최경미</span>                        <span class=\"date\">2022-05-03 08:55:13</span>","link":"https://www.bloter.net/newsView/blt202205030003","retrieved":1651548244988,"image":"https://www.bloter.net/data/blt/image/2022/05/03/blt202205030001.407x229.0.jpg"},{"title":"애플 페이만 되는 아이폰…EU, 반독점법 위반 혐의 조사","contents":"<span class=\"writer\">최경미</span>                        <span class=\"date\">2022-05-03 07:58:17</span>","link":"https://www.bloter.net/newsView/blt202205030001","retrieved":1651548244989,"image":"https://www.bloter.net/data/blt/image/2022/04/25/blt202204250002.407x229.0.jpg"}]}