{"title":"블로터 ─ 비즈니스 ─ 헤드라인","url":"https://www.bloter.net/section?id=sectionBusiness2","favicon":"https://www.bloter.net/favicon.png","elements":[{"title":"서울반도체, 2분기 가까스로 흑자...늘어난 운전자본·차입금 '관리 필요'","contents":"<span class=\"writer\">구태우</span>                        <span class=\"date\">2022-08-11 13:13:17</span>","link":"https://www.bloter.net/newsView/blt202208110006","retrieved":1660191962663,"image":"https://www.bloter.net/data/blt/image/2022/08/11/blt202208110013.570x320.0.jpg"},{"title":"연속 적자 서울반도체, 수요 감소에 '재고 관리'도 어렵다","contents":"<span class=\"writer\">최창원</span>                        <span class=\"date\"></span>","link":"https://www.bloter.net/newsView/blt202205100113","retrieved":1660191962664},{"title":"원가 부담 높아진 서울반도체, 1분기 실적에도 반영됐나","contents":"<span class=\"writer\">최창원</span>                        <span class=\"date\"></span>","link":"https://www.bloter.net/newsView/blt202204110041","retrieved":1660191962666},{"title":"서울반도체 '자동차 사업부', 독일로 옮겼다...유럽 시장 집중","contents":"<span class=\"writer\">최창원</span>                        <span class=\"date\"></span>","link":"https://www.bloter.net/newsView/blt202203300008","retrieved":1660191962671}]}