{"title":"블로터 ─ 비즈니스 ─ 헤드라인","url":"https://www.bloter.net/section?id=sectionBusiness2","favicon":"https://www.bloter.net/favicon.png","elements":[{"title":"SK이노, 배터리 사업 사상 첫 분기 매출 1조 돌파","contents":"<span class=\"writer\">김성진</span>                        <span class=\"date\">2022-01-28 12:05:48</span>","link":"https://www.bloter.net/newsView/blt202201280052","retrieved":1643339707053,"image":"https://www.bloter.net/data/blt/image/2022/01/28/blt202201280019.570x320.0.png"},{"title":"'규모의 경제'에 올인 SK이노베이션, 포드 합작사에 5조 투자","contents":"<span class=\"writer\">구태우</span>                        <span class=\"date\"></span>","link":"https://www.bloter.net/newsView/blt202109280004","retrieved":1643339707071},{"title":"SK이노베이션, 배터리 분사 통과...김준 \"SK배터리 지분 높게 유지한다\"","contents":"<span class=\"writer\">구태우</span>                        <span class=\"date\"></span>","link":"https://www.bloter.net/newsView/blt202109160023","retrieved":1643339707073},{"title":"SK이노베이션, '전기차 시장'서 삼성SDI 추월...'침투가격 전략'의 힘","contents":"<span class=\"writer\">구태우</span>                        <span class=\"date\"></span>","link":"https://www.bloter.net/newsView/blt202109010019","retrieved":1643339707077},{"title":"SK이노베이션 \"ESG 완성, 글로벌 모범 거버넌스 확보\"","contents":"<span class=\"writer\">채성오</span>                        <span class=\"date\"></span>","link":"https://www.bloter.net/newsView/blt202108080003","retrieved":1643339707078}]}