{"title":"블로터 ─ 비즈니스 ─ 헤드라인","url":"https://www.bloter.net/section?id=sectionBusiness2","favicon":"https://www.bloter.net/favicon.png","elements":[{"title":"대출이자 낮추고 투자수익 높이는 핀테크","contents":"<span class=\"writer\">강승혁</span>                        <span class=\"date\">2022-05-11 16:54:44</span>","link":"https://www.bloter.net/newsView/blt202205110153","retrieved":1652257425389,"image":"https://www.bloter.net/data/blt/image/2022/05/11/blt202205110019.570x320.0.jpg"},{"title":"직접 계산하는 'DSR 계산기' 버려도 된다…핀다는 '알아서 계산'","contents":"<span class=\"writer\">강승혁</span>                        <span class=\"date\"></span>","link":"https://www.bloter.net/newsView/blt202204280032","retrieved":1652257425390},{"title":"광주은행은 핀다, 전북은행은 고팍스…핀테크 관심많은 JB금융","contents":"<span class=\"writer\">강승혁</span>                        <span class=\"date\"></span>","link":"https://www.bloter.net/newsView/blt202203160551","retrieved":1652257425392},{"title":"쉬운 이자장사는 하기 싫다…제도권 진입한 온투업체의 '반란'","contents":"<span class=\"writer\">강승혁</span>                        <span class=\"date\"></span>","link":"https://www.bloter.net/newsView/blt202203030140","retrieved":1652257425395},{"title":"'한국판 펀딩소사이어티스' 윙크스톤파트너스, 자영업자 대출 돕는다","contents":"<span class=\"writer\">유경아</span>                        <span class=\"date\"></span>","link":"https://www.bloter.net/newsView/blt202112110004","retrieved":1652257425403}]}