{"title":"블로터 ─ 비즈니스 ─ 헤드라인","url":"https://www.bloter.net/section?id=sectionBusiness2","favicon":"https://www.bloter.net/favicon.png","elements":[{"title":"LG화학, 선택의 시간 다가오나…지분매각 열쇠 쥔 차동석 CFO","contents":"<span class=\"writer\">김성진</span>                        <span class=\"date\">2022-11-23 17:26:36</span>","link":"https://www.bloter.net/newsView/blt202211230011","retrieved":1669195040196,"image":"https://www.bloter.net/data/blt/image/2022/11/23/blt202211230018.570x320.0.jpg"},{"title":"LG화학 차동석 CFO 사장 승진...첨단소재·생명과학 승진자 '눈길'","contents":"<span class=\"writer\">구태우</span>                        <span class=\"date\"></span>","link":"https://www.bloter.net/newsView/blt202211230010","retrieved":1669195040204},{"title":"⑤글로벌 제약사 꿈꾸는 LG화학…수익성 창출 ‘과제’","contents":"<span class=\"writer\">안치영</span>                        <span class=\"date\"></span>","link":"https://www.bloter.net/newsView/blt202211150009","retrieved":1669195040206},{"title":"'뿔난 주주들' 설득 나선 차동석 LG화학 CFO","contents":"<span class=\"writer\">김성진</span>                        <span class=\"date\"></span>","link":"https://www.bloter.net/newsView/blt202010210016","retrieved":1669195040211}]}