{"title":"블로터 ─ 비즈니스 ─ 헤드라인","url":"https://www.bloter.net/section?id=sectionBusiness2","favicon":"https://www.bloter.net/favicon.png","elements":[{"title":"에쓰오일, 고유가 잭팟…'7조 규모' 샤힌 프로젝트 힘받나","contents":"<span class=\"writer\">김성진</span>                        <span class=\"date\">2022-07-28 10:34:37</span>","link":"https://www.bloter.net/newsView/blt202207280008","retrieved":1658979810131,"image":"https://www.bloter.net/data/blt/image/2022/07/28/blt202207280009.570x320.0.jpg"},{"title":"에쓰오일과 수소 사업 협력 맺은 삼성물산...빅픽처는?","contents":"<span class=\"writer\">구태우</span>                        <span class=\"date\"></span>","link":"https://www.bloter.net/newsView/blt202109220001","retrieved":1658979810132},{"title":"에쓰오일도 ‘수소사업’ 올라탔다","contents":"<span class=\"writer\">김성진</span>                        <span class=\"date\"></span>","link":"https://www.bloter.net/newsView/blt202103070005","retrieved":1658979810136},{"title":"에쓰오일 새 CFO 방주완 “7조 투자 상당폭 절감한다”","contents":"<span class=\"writer\">김성진</span>                        <span class=\"date\"></span>","link":"https://www.bloter.net/newsView/blt202101280020","retrieved":1658979810138},{"title":"‘친환경이 대세’…에쓰오일, 저탄소 투자로드맵 수립","contents":"<span class=\"writer\">김성진</span>                        <span class=\"date\"></span>","link":"https://www.bloter.net/newsView/blt202012200003","retrieved":1658979810140}]}