{"title":"블로터 ─ 비즈니스 ─ 헤드라인","url":"https://www.bloter.net/section?id=sectionBusiness2","favicon":"https://www.bloter.net/favicon.png","elements":[{"title":"IT강국서 '99%'가 아날로그인 실손보험 청구…국힘이 살펴본다","contents":"<span class=\"writer\">강승혁</span>                        <span class=\"date\">2022-08-22 17:51:07</span>","link":"https://www.bloter.net/newsView/blt202208220016","retrieved":1661159819865,"image":"https://www.bloter.net/data/blt/image/2022/08/22/blt202208220033.570x320.0.jpg"},{"title":"캐롯손해보험, 연내 3000억 증자 예정…'양식 유니콘'의 탄생?","contents":"<span class=\"writer\">강승혁</span>                        <span class=\"date\"></span>","link":"https://www.bloter.net/newsView/blt202208220010","retrieved":1661159819870},{"title":"⑤디지털 전환에 진심인 메리츠화재…\"보험료 산출시간 1/60로 줄였죠\"","contents":"<span class=\"writer\">강승혁</span>                        <span class=\"date\"></span>","link":"https://www.bloter.net/newsView/blt202208180021","retrieved":1661159819878},{"title":"④신한금융이 '신한EZ손해보험'만으로 만족 못하는 이유는?","contents":"<span class=\"writer\">강승혁</span>                        <span class=\"date\"></span>","link":"https://www.bloter.net/newsView/blt202208170023","retrieved":1661159819878},{"title":"저연령화하는 '학교폭력'…디지털 청소년보험 출시 늘어나는 이유","contents":"<span class=\"writer\">강승혁</span>                        <span class=\"date\"></span>","link":"https://www.bloter.net/newsView/blt202208160020","retrieved":1661159819880}]}