{"title":"블로터 ─ 비즈니스 ─ 헤드라인","url":"https://www.bloter.net/section?id=sectionBusiness2","favicon":"https://www.bloter.net/favicon.png","elements":[{"title":"광주은행은 핀다, 전북은행은 고팍스…핀테크 관심많은 JB금융","contents":"<span class=\"writer\">강승혁</span>                        <span class=\"date\">2022-03-16 18:26:49</span>","link":"https://www.bloter.net/newsView/blt202203160551","retrieved":1647425938997,"image":"https://www.bloter.net/data/blt/image/2022/03/16/blt202203160035.570x320.0.jpg"},{"title":"우주의 기운 몰리는 고팍스...실명계좌·투자 이어 거래량 잡을까","contents":"<span class=\"writer\">강승혁</span>                        <span class=\"date\"></span>","link":"https://www.bloter.net/newsView/blt202202240235","retrieved":1647425938999},{"title":"핀다의 혁신금융, 금융위에 '중금리대출' 박씨 물어다줬다","contents":"<span class=\"writer\">강승혁</span>                        <span class=\"date\"></span>","link":"https://www.bloter.net/newsView/blt202202230143","retrieved":1647425939001},{"title":"비금융정보로 대출기회 넓히려는 핀다…LG전자 '데이터통' 영입","contents":"<span class=\"writer\">강승혁</span>                        <span class=\"date\"></span>","link":"https://www.bloter.net/newsView/blt202201170062","retrieved":1647425939003},{"title":"보릿고개 문제 없다...고팍스·후오비코리아 생존 전략은?","contents":"<span class=\"writer\">이건한</span>                        <span class=\"date\"></span>","link":"https://www.bloter.net/newsView/blt202109270111","retrieved":1647425939006}]}