{"title":"블로터 ─ 비즈니스","url":"https://www.bloter.net/section?id=sectionBusiness2","favicon":"https://www.bloter.net/favicon.png","elements":[{"title":"세계 파운드리 10위 기업 DB하이텍, '5G 장비' 사업 확대한다","contents":"<span class=\"writer\">이일호</span>                        <span class=\"date\">2022-01-12 12:37:49</span>","link":"https://www.bloter.net/newsView/blt202201120005","retrieved":1642017574870,"image":"https://www.bloter.net/data/blt/image/2022/01/12/blt202201120007.407x229.0.jpg"},{"title":"‘OLED가 실내를 감싸네’..LG전자, 벤츠 전기차에 인포테인먼트 시스템 공급","contents":"<span class=\"writer\">이일호</span>                        <span class=\"date\">2022-01-12 12:02:17</span>","link":"https://www.bloter.net/newsView/blt202201120008","retrieved":1642017574878,"image":"https://www.bloter.net/data/blt/image/2022/01/12/blt202201120011.407x229.0.jpg"},{"title":"트위터, 보기 싫은 계정·콘텐츠 숨기기 기능 강화한다","contents":"<span class=\"writer\">최경미</span>                        <span class=\"date\">2022-01-12 10:16:49</span>","link":"https://www.bloter.net/newsView/blt202201120006","retrieved":1642017574881,"image":"https://www.bloter.net/data/blt/image/2022/01/12/blt202201120008.407x229.0.png"},{"title":"美 법원, FTC의 페이스북 반독점 소송 진행 승인","contents":"<span class=\"writer\">최경미</span>                        <span class=\"date\">2022-01-12 09:55:38</span>","link":"https://www.bloter.net/newsView/blt202201120004","retrieved":1642017574883,"image":"https://www.bloter.net/data/blt/image/2022/01/12/blt202201120005.407x229.0.jpg"},{"title":"‘무노조 경영’ 이어온 아마존, 첫 노조 설립 찬반 재투표 실시","contents":"<span class=\"writer\">최경미</span>                        <span class=\"date\">2022-01-12 08:29:50</span>","link":"https://www.bloter.net/newsView/blt202201120001","retrieved":1642017574884,"image":"https://www.bloter.net/data/blt/image/2022/01/12/blt202201120003.407x229.0.png"},{"title":"AI·메타버스·구독 투자 앞둔 SKT, 곳간 따져보니","contents":"<span class=\"writer\">박현준</span>                        <span class=\"date\">2022-01-11 17:41:42</span>","link":"https://www.bloter.net/newsView/blt202201110062","retrieved":1642017574889,"image":"https://www.bloter.net/data/blt/image/2022/01/11/blt202201110021.407x229.0.jpg"}]}