{"title":"블로터 ─ 비즈니스","url":"https://www.bloter.net/section?id=sectionBusiness2","favicon":"https://www.bloter.net/favicon.png","elements":[{"title":"中, 제로 코로나 시위 소식 '쉬쉬'...해외SNS 앱 설치 단속나섰다","contents":"<span class=\"writer\">최경미</span>                        <span class=\"date\">2022-11-29 08:40:10</span>","link":"https://www.bloter.net/newsView/blt202211290002","retrieved":1669706162078,"image":"https://www.bloter.net/data/blt/image/2022/11/29/blt202211290001.407x229.0.png"},{"title":"너무 중앙화된 업비트…어느새 쥔 블록체인 프로젝트 '생사여탈권'","contents":"<span class=\"writer\">강승혁</span>                        <span class=\"date\">2022-11-28 16:00:56</span>","link":"https://www.bloter.net/newsView/blt202211280011","retrieved":1669698961902,"image":"https://www.bloter.net/data/blt/image/2022/11/28/blt202211280020.407x229.0.jpg"},{"title":"④수익부터 챙긴 CJ프레시웨이…3조 매출 재정복 가능할까","contents":"<span class=\"writer\">김성진</span>                        <span class=\"date\">2022-11-28 15:39:24</span>","link":"https://www.bloter.net/newsView/blt202211280010","retrieved":1669684627629,"image":"https://www.bloter.net/data/blt/image/2022/11/28/blt202211280015.407x229.0.jpg"},{"title":"최윤범의 고려아연판 '무자본 M&A'...신사업으로 투자 기회·거버넌스 '일거양득'","contents":"<span class=\"writer\">구태우</span>                        <span class=\"date\">2022-11-28 15:38:47</span>","link":"https://www.bloter.net/newsView/blt202211280004","retrieved":1669684627630,"image":"https://www.bloter.net/data/blt/image/2022/11/28/blt202211280009.407x229.0.jpeg"},{"title":"일론 머스크 \"트위터, 하루 200만명씩 가입했다\"","contents":"<span class=\"writer\">최경미</span>                        <span class=\"date\">2022-11-28 10:20:32</span>","link":"https://www.bloter.net/newsView/blt202211280003","retrieved":1669684627631,"image":"https://www.bloter.net/data/blt/image/2022/11/28/blt202211280004.407x229.0.png"},{"title":"美 블랙프라이데이, 온라인 매출만 12조…사상 최대치 기록","contents":"<span class=\"writer\">최경미</span>                        <span class=\"date\">2022-11-28 09:48:41</span>","link":"https://www.bloter.net/newsView/blt202211280002","retrieved":1669623680474,"image":"https://www.bloter.net/data/blt/image/2022/11/28/blt202211280003.407x229.0.png"}]}