{"title":"블로터 ─ 비즈니스 ─ 헤드라인","url":"https://www.bloter.net/section?id=sectionBusiness2","favicon":"https://www.bloter.net/favicon.png","elements":[{"title":"유튜브 뛰어넘은 틱톡…전 세계 아동·청소년 사용 시간 1위","contents":"<span class=\"writer\">최경미</span>                        <span class=\"date\">2023-02-08 08:57:25</span>","link":"https://www.bloter.net/newsView/blt202302080003","retrieved":1675818758146,"image":"https://www.bloter.net/data/blt/image/2023/02/08/blt202302080003.570x320.0.png"},{"title":"美 대학으로 확산하는 틱톡 퇴출 움직임...학생들은 분노","contents":"<span class=\"writer\">최경미</span>                        <span class=\"date\"></span>","link":"https://www.bloter.net/newsView/blt202301270015","retrieved":1675818758147},{"title":"美서 틱톡 '현대·기아차 절도 챌린지' 인기…도난 급증","contents":"<span class=\"writer\">최경미</span>                        <span class=\"date\"></span>","link":"https://www.bloter.net/newsView/blt202301130020","retrieved":1675818758151},{"title":"美하원 중국특별위원장 내정자 \"틱톡은 마약…미국 내 사용 금지해야\"","contents":"<span class=\"writer\">최경미</span>                        <span class=\"date\"></span>","link":"https://www.bloter.net/newsView/blt202301030002","retrieved":1675818758151},{"title":"美 상·하원, 틱톡 금지 법안 발의…미국 내 서비스 중단될까","contents":"<span class=\"writer\">최경미</span>                        <span class=\"date\"></span>","link":"https://www.bloter.net/newsView/blt202212140003","retrieved":1675818758156}]}