{"title":"블로터 ─ 비즈니스 ─ 헤드라인","url":"https://www.bloter.net/section?id=sectionBusiness2","favicon":"https://www.bloter.net/favicon.png","elements":[{"title":"‘보릿고개’ SK하이닉스, 버티는 힘이 더 중요해진 이유","contents":"<span class=\"writer\">이원종</span>                        <span class=\"date\">2023-02-09 16:00:01</span>","link":"https://www.bloter.net/newsView/blt202302090014","retrieved":1675926876221,"image":"https://www.bloter.net/data/blt/image/2023/02/09/blt202302090198.570x320.0.png"},{"title":"SK하이닉스, 15.6조원 재고 처리 ‘고민’…관리비용 부담 어쩌나","contents":"<span class=\"writer\">김수민</span>                        <span class=\"date\"></span>","link":"https://www.bloter.net/newsView/blt202302070007","retrieved":1675926876233},{"title":"SK하이닉스, 1.7조원 영업손실에도 재무건전성 양호한 이유","contents":"<span class=\"writer\">김수민</span>                        <span class=\"date\"></span>","link":"https://www.bloter.net/newsView/blt202302040002","retrieved":1675926876234},{"title":"SK하이닉스, '반도체 불황' 속 실적 반등 기대하는 이유…중국·인텔 CPU·챗GPT","contents":"<span class=\"writer\">박현준</span>                        <span class=\"date\"></span>","link":"https://www.bloter.net/newsView/blt202302010007","retrieved":1675926876234},{"title":"SK하이닉스, 해외서 1.2조원 조달…‘지속가능연계채권’ 뭐길래","contents":"<span class=\"writer\">김수민</span>                        <span class=\"date\"></span>","link":"https://www.bloter.net/newsView/blt202301110007","retrieved":1675926876246}]}