{"title":"블로터 ─ 컬처","url":"https://www.bloter.net/section?id=sectionCulture","favicon":"https://www.bloter.net/favicon.png","elements":[{"title":"[단독]'소년심판'도 시즌2 제작…넷플릭스, 韓 오리지널 집중도 높인다","contents":"소년범죄를 사실감 있게 다뤘던 넷플릭스 오리지널 시리즈 '소년심판'이 시즌2로 돌아온다.1일 &lt;블로터&gt; 취재 결과, 소년심판 시즌2가 올해 8~9월 사이 프리프로덕션에 돌입한다. 프리프로덕션은 촬영 전 프로덕션을 준비하는 단계로 제작진 구성, 배역 확정, 장","link":"https://www.bloter.net/newsView/blt202208010017","retrieved":1659357276897,"image":"https://www.bloter.net/data/blt/image/2022/08/01/blt202208010048.293x165.0.jpg"},{"title":"[현장+]모바일 밖으로 나온 29CM, '이구갤러리' 찾는 MZ세대","contents":"1일 오전 10시 30분 서울 여의도 소재 더현대서울에 위치한 '이구갤러리'는 오픈 후 몇 분 지나지 않아 매장을 둘러보는 고객들로 채워졌다. MZ세대를 겨냥한 이색 브랜드가 위치한 지하 2층 '크리에이티브 그라운드' 한 켠에 자리잡은 만큼 이구갤러리의 고객은 대부","link":"https://www.bloter.net/newsView/blt202208010016","retrieved":1659357276899,"image":"https://www.bloter.net/data/blt/image/2022/08/01/blt202208010046.293x165.0.jpg"},{"title":"[공시분석]제조사 '에이치앤비디자인'은 왜 부동산 기업을 인수할까","contents":"알아두면 도움이 될 의미있는 공시를 소개·분석 합니다.  공시 요약 오늘 소개할 공시는 '에이치앤비디자인'이 1일 공시한 '타법인 주식 및 출자증권 양수결정'입니다. 해당 공시는 에이치앤비디자인이 '대한종건'의 주식 100%를 200억원에 인수한다는 내용입니다","link":"https://www.bloter.net/newsView/blt202208010014","retrieved":1659345724040,"image":"https://www.bloter.net/data/blt/image/2022/08/01/blt202208010032.293x165.0.jpg"},{"title":"수출업황 나빠져도…'K콘텐츠'는 살아남을까","contents":"원재료 가격 상승과 원화환율 불안정 등으로 수출 환경이 악화하는 가운데서도 '문화콘텐츠' 분야는 긍정적인 기대가 나오고 있다. 문화콘텐츠는 인간의 창의성과 지식을 원재료로 사용해 고부가가치를 창출할 수 있는 산업이다.1일 한국수출입은행의 '2022년 2분기","link":"https://www.bloter.net/newsView/blt202208010013","retrieved":1659345724042,"image":"https://www.bloter.net/data/blt/image/2022/08/01/blt202208010030.293x165.0.jpg"},{"title":"넷플릭스, '비공식 브리저튼 뮤지컬' 창작자 고소","contents":"넷플릭스가 '브리저튼' 테마 뮤지컬을 만든 창작자들을 고소했다. 오리지널 시리즈 브리저튼에 대한 저작권 침해 혐의다. 지난달 30일(현지시간) 미국 엔터테인먼트 매체인 &lt;데드라인&gt; 등에 따르면, 넷플릭스가 비공식 브리저튼 뮤지컬을 창작한 '애비게일 발로","link":"https://www.bloter.net/newsView/blt202208010001","retrieved":1659318642741,"image":"https://www.bloter.net/data/blt/image/2022/08/01/blt202208010001.293x165.0.png"},{"title":"[오~컬쳐]韓 개발사 만든 '블루아카이브', 서브컬쳐 본고장 역주행","contents":"넥슨게임즈의 서브컬쳐 게임 '블루아카이브'가 일본에서 흥행 역주행 기록을 써내려 가고 있다. MX스튜디오가 개발한 블루아카이브는 지난 21일 일본 애플 앱스토어에서 매출 순위 2위를 기록했고 같은 달 26일의 경우 구글플레이 스토어 3위에 올랐다. 해당 순위는","link":"https://www.bloter.net/newsView/blt202207310001","retrieved":1659262758418,"image":"https://www.bloter.net/data/blt/image/2022/07/31/blt202207310005.293x165.0.jpg"},{"title":"[공시분석]'진퇴양난' CJ CGV, CJ에 기댄 '유상증자'","contents":"알아두면 도움이 될 의미있는 공시를 소개·분석 합니다. 공시 요약 오늘 소개할 공시는 CJ CGV가 지난 28일 공시한 '유상증자 또는 주식관련사채 등의 발행결과'입니다. 공시 내용은 지난 8일 최대주주인 CJ에 대해 실시한 1500억원 규모의 제3자 배정 유상증자 납입","link":"https://www.bloter.net/newsView/blt202207300004","retrieved":1659172616336,"image":"https://www.bloter.net/data/blt/image/2022/07/30/blt202207300006.293x165.0.png"},{"title":"[현장+]'고객 우선' 외친 발란, 오프라인 매장으로 '재도약' 시동","contents":"지난 28일 오후 서울 여의도 IFC몰에서 발란의 '커넥티드 스토어' 1호점이 베일을 벗었다. 가장 먼저 눈길을 사로잡은 것은 노출 천장 및 콘크리트와 메탈 소재, 그래픽 등의 인테리어였다. 큼지막하고 간결한 로고로 알려진 발란의 애플리케이션(앱) 화면이나 명품 매","link":"https://www.bloter.net/newsView/blt202207290005","retrieved":1659086330727,"image":"https://www.bloter.net/data/blt/image/2022/07/29/blt202207290035.293x165.0.jpg"},{"title":"[마켓리뷰]데브시스터즈, 우울한 2분기?…디즈니 콜라보 빨랐다면","contents":"마켓리뷰는 기업의 분기별 사업활동을 살펴보고 시장 전망을 통해 실적을 예측해보는 코너입니다. 사업 성과와 신사업 계획을 더해 기업 성장 가능성을 짚어봅니다. '쿠키런: 킹덤'의 매출 하향 안정화 기조가 계속되며 데브시스터즈의 성장 동력도 약해진 모습이","link":"https://www.bloter.net/newsView/blt202207290009","retrieved":1659075825385,"image":"https://www.bloter.net/data/blt/image/2022/07/29/blt202207290016.293x165.0.jpg"},{"title":"인스타그램, '틱톡 표절' 제기된 '홈 피드 개편안' 철회","contents":"인스타그램이 최근 사용자들로부터 거센 비난을 받은 홈 피드 개편안을 철회한다고 발표했다. 28일(현지시간) 아담 모세리 인스타그램 최고경영자(CEO)는 IT 뉴스레터 &lt;플랫포머&gt;와의 인터뷰에서 현재 시범 운영 중인 인스타그램 전체 화면 홈 피드 개편을 몇 주","link":"https://www.bloter.net/newsView/blt202207290003","retrieved":1659059232986,"image":"https://www.bloter.net/data/blt/image/2022/07/29/blt202207290005.293x165.0.png"},{"title":"크래프톤 또 퇴출?…구글·애플서 삭제된 '배그 모바일 인도'","contents":"크래프톤이 인도 지역에서 출시한 모바일 게임 '배틀그라운드 모바일 인도'(BGMI)가 인도 구글 플레이와 애플 앱스토어에서 삭제(차단)된 것으로 확인됐다. 2020년 '배틀그라운드 모바일'이 퇴출당한지 약 2년 만이다. 28일(현지시간) IT 전문매체 &lt;테크크런치&gt;는 구","link":"https://www.bloter.net/newsView/blt202207290002","retrieved":1659059232989,"image":"https://www.bloter.net/data/blt/image/2022/07/29/blt202207290003.293x165.0.jpeg"},{"title":"[LCK, 이렇게 바뀐다]③지정선수 특별협상으로 본 '이적시장'","contents":"'리그 오브 레전드 챔피언스코리아'(이하 LCK)가 신규 제도 도입을 통해 '지속가능성'을 확보한다고 밝혔습니다. 신인 발굴을 위한 '육성권' 제도부터 '공인 에이전트 제도화' 및 '지정선수 특별협상'으로 리그 경쟁력을 강화한다는 계획인데요. &lt;블로터&gt;는 LCK의","link":"https://www.bloter.net/newsView/blt202207280024","retrieved":1658999950523,"image":"https://www.bloter.net/data/blt/image/2022/07/28/blt202207280036.293x165.0.jpg"}]}