{"title":"블로터 ─ 컬처 ─ 헤드라인","url":"https://www.bloter.net/section?id=sectionCulture","favicon":"https://www.bloter.net/favicon.png","elements":[{"title":"[오~컬쳐]'펄어비스'는 여전히 '검은사막'이 필요하다","contents":"<span class=\"writer\">채성오</span>\n                        <span class=\"date\">2022-02-15 15:13:50</span>","link":"https://www.bloter.net/newsView/blt202202150052","retrieved":1644905990022,"image":"https://www.bloter.net/data/blt/image/2022/02/15/blt202202150021.601x301.0.jpg"},{"title":"[오~컬쳐]엔씨표 메타버스는 '미니버스'?…신사업 추진 가속화되나","contents":"<span class=\"writer\">채성오</span>\n                        <span class=\"date\">2022-02-15 10:47:56</span>","link":"https://www.bloter.net/newsView/blt202202150021","retrieved":1644895000545,"image":"https://www.bloter.net/data/blt/image/2022/02/15/blt202202150012.282x159.0.jpg"},{"title":"[오~컬쳐]'쿠키런: 킹덤' 덕본 데브시스터즈, 지속성장 가능할까","contents":"<span class=\"writer\">채성오</span>\n                        <span class=\"date\">2022-02-14 18:38:18</span>","link":"https://www.bloter.net/newsView/blt202202140307","retrieved":1644895000546,"image":"https://www.bloter.net/data/blt/image/2022/02/14/blt202202140029.282x159.0.jpg"},{"title":"[오~컬쳐]컴투스 코인 'C2X' 3월 상장…최대 거래소 '바이낸스'로 향할까","contents":"<span class=\"writer\">채성오</span>\n                        <span class=\"date\">2022-02-11 16:38:19</span>","link":"https://www.bloter.net/newsView/blt202202110213","retrieved":1644567485161,"image":"https://www.bloter.net/data/blt/image/2022/02/11/blt202202110019.282x159.0.jpg"}]}