{"title":"블로터 ─ 컬처 ─ 헤드라인","url":"https://www.bloter.net/section?id=sectionCulture","favicon":"https://www.bloter.net/favicon.png","elements":[{"title":"[오~컬쳐]급여·배당금 올인하는 장현국, '위믹스 살리기' 시동건다","contents":"<span class=\"date\"></span>","link":"https://www.bloter.net/newsView/blt202204130135","retrieved":1649874420185,"image":"https://www.bloter.net/data/blt/image/2022/04/13/blt202204130044.601x301.0.jpg"},{"title":"[게임인사이드]'로스트아크' 어디까지 성장할까","contents":"<span class=\"writer\">채성오</span>\n                        <span class=\"date\">2022-04-13 18:17:56</span>","link":"https://www.bloter.net/newsView/blt202204130133","retrieved":1649874420187,"image":"https://www.bloter.net/data/blt/image/2022/04/13/blt202204130040.282x159.0.png"},{"title":"[게임인사이드]성장한 만큼 올려달라는 노조, 웹젠은 응답할까","contents":"<span class=\"writer\">채성오</span>\n                        <span class=\"date\">2022-04-11 19:27:28</span>","link":"https://www.bloter.net/newsView/blt202204110288","retrieved":1649874420188,"image":"https://www.bloter.net/data/blt/image/2022/04/11/blt202204110021.282x159.0.jpg"},{"title":"[현장+]팬덤 플랫폼 '위버스'의 진화…BTS도 반했다","contents":"<span class=\"writer\">미국 라스베이거스=안신혜</span>\n                        <span class=\"date\">2022-04-11 14:22:16</span>","link":"https://www.bloter.net/newsView/blt202204110033","retrieved":1649874420190,"image":"https://www.bloter.net/data/blt/image/2022/04/11/blt202204110009.282x159.0.jpg"}]}