{"title":"블로터 ─ 테크","url":"https://www.bloter.net/section?id=sectionTech","favicon":"https://www.bloter.net/favicon.png","elements":[{"title":"DB하이텍, 유동성 역대 최대…투자 없이 현금만 쌓아","contents":"<span class=\"writer\">김수민</span>                        <span class=\"date\">2022-09-04 10:04:08</span>","link":"https://www.bloter.net/newsView/blt202209010015","retrieved":1662255950801,"image":"https://www.bloter.net/data/blt/image/2022/09/01/blt202209010025.620x344.0.png"},{"title":"광물 자원 부족 겪는 미국, 전기차 보급 확대에 차질 생기나","contents":"<span class=\"writer\">최경미</span>                        <span class=\"date\">2022-09-04 09:00:02</span>","link":"https://www.bloter.net/newsView/blt202209020023","retrieved":1662255950801,"image":"https://www.bloter.net/data/blt/image/2022/09/02/blt202209020037.290x163.0.png"},{"title":"커리어 성장도 온라인으로...커지는 강의 플랫폼 시장","contents":"<span class=\"writer\">최창원</span>                        <span class=\"date\">2022-09-03 17:00:02</span>","link":"https://www.bloter.net/newsView/blt202208310019","retrieved":1662193272444,"image":"https://www.bloter.net/data/blt/image/2022/08/31/blt202208310031.290x163.0.jpg"},{"title":"[현장+] 광고, 다시 TV로…CTV 시대를 준비하라","contents":"<span class=\"writer\">유다정</span>                        <span class=\"date\">2022-09-03 15:00:02</span>","link":"https://www.bloter.net/newsView/blt202208260014","retrieved":1662186123631,"image":"https://www.bloter.net/data/blt/image/2022/08/26/blt202208260033.290x163.0.jpg"},{"title":"[테크체인저]\"농수산물, 직거래하면 안돼?\"...레드오션 뚫어낸 팔도감","contents":"<span class=\"writer\">최창원</span>                        <span class=\"date\">2022-09-03 13:00:02</span>","link":"https://www.bloter.net/newsView/blt202208310002","retrieved":1662177863646,"image":"https://www.bloter.net/data/blt/image/2022/08/31/blt202208310002.290x163.0.jpg"},{"title":"LF의 온라인 실험, '헤지스닷컴'은 어떻게 '버티컬 플랫폼화' 됐나","contents":"<span class=\"writer\">안신혜</span>                        <span class=\"date\">2022-09-03 12:00:01</span>","link":"https://www.bloter.net/newsView/blt202209020028","retrieved":1662177863647,"image":"https://www.bloter.net/data/blt/image/2022/09/02/blt202209020044.290x163.0.jpg"},{"title":"용두사미 ‘K-바이오 백신 펀드’…5000억원이 1000억원으로 ‘축소’","contents":"<span class=\"writer\">안치영</span>                        <span class=\"date\">2022-09-03 11:00:02</span>","link":"https://www.bloter.net/newsView/blt202209020024","retrieved":1662177863649,"image":"https://www.bloter.net/data/blt/image/2022/09/02/blt202209020039.290x163.0.png"},{"title":"애플, 9월 7일 신제품 공개 행사…관전 포인트는?","contents":"<span class=\"writer\">최경미</span>                        <span class=\"date\">2022-09-03 09:00:02</span>","link":"https://www.bloter.net/newsView/blt202209020022","retrieved":1662169743295,"image":"https://www.bloter.net/data/blt/image/2022/09/02/blt202209020034.290x163.0.png"},{"title":"해외매출이 국내매출 앞지른 '데브시스터즈', 향후 과제는?","contents":"<span class=\"writer\">안신혜</span>                        <span class=\"date\">2022-09-02 18:24:32</span>","link":"https://www.bloter.net/newsView/blt202209010025","retrieved":1662114017072,"image":"https://www.bloter.net/data/blt/image/2022/09/01/blt202209010046.290x163.0.png"},{"title":"[마켓리뷰]'뮤' 매출 의존도 심화…웹젠, '돌파구' 찾을 수 있나","contents":"<span class=\"writer\">채성오</span>                        <span class=\"date\">2022-09-02 17:40:29</span>","link":"https://www.bloter.net/newsView/blt202209020020","retrieved":1662110276317,"image":"https://www.bloter.net/data/blt/image/2022/09/02/blt202209020026.290x163.0.jpg"},{"title":"단순 매출증가? 스카이라이프TV·미디어지니 합병 기대 효과는","contents":"<span class=\"writer\">이건한</span>                        <span class=\"date\">2022-09-02 17:22:09</span>","link":"https://www.bloter.net/newsView/blt202209020019","retrieved":1662106950608,"image":"https://www.bloter.net/data/blt/image/2022/09/02/blt202209020024.290x163.0.png"},{"title":"오늘회 '전직원 권고사직'...커지는 스타트업 '적자 성장' 우려","contents":"<span class=\"writer\">최창원</span>                        <span class=\"date\">2022-09-02 17:19:25</span>","link":"https://www.bloter.net/newsView/blt202209020021","retrieved":1662106950615,"image":"https://www.bloter.net/data/blt/image/2022/09/02/blt202209020032.290x163.0.png"},{"title":"코로나19 백신 접종, 국내서도 유료화되나","contents":"<span class=\"writer\">안치영</span>                        <span class=\"date\">2022-09-02 15:35:15</span>","link":"https://www.bloter.net/newsView/blt202209020010","retrieved":1662101415808,"image":"https://www.bloter.net/data/blt/image/2022/09/02/blt202209020015.290x163.0.jpg"},{"title":"LG전자 '오브제 무드업' 신제품 출시...\"냉장고야 분위기를 부탁해\"","contents":"<span class=\"writer\">구태우</span>                        <span class=\"date\">2022-09-02 13:51:10</span>","link":"https://www.bloter.net/newsView/blt202209020009","retrieved":1662098465432,"image":"https://www.bloter.net/data/blt/image/2022/09/02/blt202209020010.290x163.0.jpg"},{"title":"서울바이오시스, IFA서 적층형 구조 마이크로 LED 공개...'초격차란 이런 것'","contents":"<span class=\"writer\">구태우</span>                        <span class=\"date\">2022-09-02 13:46:29</span>","link":"https://www.bloter.net/newsView/blt202209020006","retrieved":1662098465432,"image":"https://www.bloter.net/data/blt/image/2022/09/02/blt202209020008.290x163.0.jpg"},{"title":"마이크론, 20조 투자해 메모리 반도체 공장 짓는다…”美 반도체법 덕분”","contents":"<span class=\"writer\">최경미</span>                        <span class=\"date\">2022-09-02 10:13:31</span>","link":"https://www.bloter.net/newsView/blt202209020003","retrieved":1662083290541,"image":"https://www.bloter.net/data/blt/image/2022/09/02/blt202209020003.290x163.0.jpeg"},{"title":"트위터, 유료 구독 서비스 ‘블루’에 ‘편집 기능’ 추가 임박","contents":"<span class=\"writer\">최경미</span>                        <span class=\"date\">2022-09-02 09:21:57</span>","link":"https://www.bloter.net/newsView/blt202209020002","retrieved":1662083290544,"image":"https://www.bloter.net/data/blt/image/2022/09/02/blt202209020002.290x163.0.jpg"},{"title":"英 반독점 당국 “MS의 액티비전 인수 경쟁 제한 우려 있다”","contents":"<span class=\"writer\">최경미</span>                        <span class=\"date\">2022-09-02 08:15:19</span>","link":"https://www.bloter.net/newsView/blt202209020001","retrieved":1662074401034,"image":"https://www.bloter.net/data/blt/image/2022/09/02/blt202209020001.290x163.0.png"}]}