{"title":"블로터 ─ 테크","url":"https://www.bloter.net/section?id=sectionTech","favicon":"https://www.bloter.net/favicon.png","elements":[{"title":"새 정부 인수위, ‘LG 클로이’ 사투리 인식여부 관심 가진 이유","contents":"<span class=\"writer\">이일호</span>                        <span class=\"date\">2022-04-20 13:27:32</span>","link":"https://www.bloter.net/newsView/blt202204200018","retrieved":1650430805220,"image":"https://www.bloter.net/data/blt/image/2022/04/20/blt202204200009.620x344.0.jpg"},{"title":"세 번째 '갤럭시 퀀텀' 등장…SKT는 왜 양자 스마트폰에 공 들이나","contents":"<span class=\"writer\">박현준</span>                        <span class=\"date\">2022-04-20 11:19:02</span>","link":"https://www.bloter.net/newsView/blt202204200014","retrieved":1650426089579,"image":"https://www.bloter.net/data/blt/image/2022/04/20/blt202204200008.290x163.0.jpg"},{"title":"우버·리프트, 美 연방법원 판결에 마스크 의무화 조치 폐지","contents":"<span class=\"writer\">최경미</span>                        <span class=\"date\">2022-04-20 10:00:54</span>","link":"https://www.bloter.net/newsView/blt202204200011","retrieved":1650418213216,"image":"https://www.bloter.net/data/blt/image/2022/04/20/blt202204200006.290x163.0.jpeg"},{"title":"WIS2022 개막...코로나19 이후 메타버스·디지털트윈·AI·자율주행 트렌드는?","contents":"<span class=\"writer\">이일호</span>                        <span class=\"date\">2022-04-20 09:58:08</span>","link":"https://www.bloter.net/newsView/blt202204200012","retrieved":1650418213219,"image":"https://www.bloter.net/data/blt/image/2022/04/20/blt202204200007.290x163.0.jpg"},{"title":"美 노사관계 기관, \"아마존, 시위 참여해 해고당한 직원 복귀시켜야\"","contents":"<span class=\"writer\">최경미</span>                        <span class=\"date\">2022-04-20 09:10:19</span>","link":"https://www.bloter.net/newsView/blt202204200006","retrieved":1650418213219,"image":"https://www.bloter.net/data/blt/image/2022/04/20/blt202204200005.290x163.0.jpg"},{"title":"LG마그나, 첫 해외공장은 멕시코...GM 전기차용 부품 생산","contents":"<span class=\"writer\">최창원</span>                        <span class=\"date\">2022-04-20 09:00:02</span>","link":"https://www.bloter.net/newsView/blt202204200003","retrieved":1650418213221,"image":"https://www.bloter.net/data/blt/image/2022/04/20/blt202204200001.290x163.0.jpg"},{"title":"넷플릭스 구독자 수 11년만에 20만명 감소…왜?","contents":"<span class=\"writer\">최경미</span>                        <span class=\"date\">2022-04-20 08:20:50</span>","link":"https://www.bloter.net/newsView/blt202204200002","retrieved":1650418213222,"image":"https://www.bloter.net/data/blt/image/2022/04/20/blt202204200002.290x163.0.png"},{"title":"[5G 3년] ④화웨이, 장비 시장은 지켰다...친환경 띄우고 B2B 솔루션 확대","contents":"<span class=\"writer\">이건한</span>                        <span class=\"date\">2022-04-20 07:09:49</span>","link":"https://www.bloter.net/newsView/blt202204190074","retrieved":1650410225883,"image":"https://www.bloter.net/data/blt/image/2022/04/19/blt202204190025.290x163.0.jpg"},{"title":"[현장+]JTBC스튜디오, 'SLL'로 리뉴얼…연매출 2조 노린다","contents":"<span class=\"writer\">채성오</span>                        <span class=\"date\">2022-04-19 20:00:03</span>","link":"https://www.bloter.net/newsView/blt202204190075","retrieved":1650366975452,"image":"https://www.bloter.net/data/blt/image/2022/04/19/blt202204190028.290x163.0.jpg"},{"title":"구글코리아의 매출은 해외로 통하는 이유","contents":"<span class=\"writer\">박현준</span>                        <span class=\"date\">2022-04-19 18:21:50</span>","link":"https://www.bloter.net/newsView/blt202204190073","retrieved":1650363750153,"image":"https://www.bloter.net/data/blt/image/2022/04/19/blt202204190024.290x163.0.jpg"},{"title":"[단독]엔픽셀, 블록체인·메타버스 사업 고도화…'메타본부' 체제 가동","contents":"<span class=\"writer\">채성오</span>                        <span class=\"date\">2022-04-19 17:44:12</span>","link":"https://www.bloter.net/newsView/blt202204190070","retrieved":1650360025985,"image":"https://www.bloter.net/data/blt/image/2022/04/19/blt202204190020.290x163.0.jpg"},{"title":"우주·모빌리티·지능형 도시…‘선 넘는 과학자들’ 지구 위한 강연 펼친다","contents":"<span class=\"writer\">정두용</span>                        <span class=\"date\">2022-04-19 17:03:40</span>","link":"https://www.bloter.net/newsView/blt202204190062","retrieved":1650356706295,"image":"https://www.bloter.net/data/blt/image/2022/04/19/blt202204190019.290x163.0.jpg"},{"title":"VM웨어 \"삼성SDS·LG CNS와 '크로스 클라우드' 연합하겠다\"","contents":"<span class=\"writer\">강승혁</span>                        <span class=\"date\">2022-04-19 16:36:22</span>","link":"https://www.bloter.net/newsView/blt202204190036","retrieved":1650356706297,"image":"https://www.bloter.net/data/blt/image/2022/04/19/blt202204190017.290x163.0.jpg"},{"title":"국내 연구진이 개발한 면역항암제 ‘길잡이’ 기술…‘게임 체인저’ 상용화 기대","contents":"<span class=\"writer\">정두용</span>                        <span class=\"date\">2022-04-19 16:03:24</span>","link":"https://www.bloter.net/newsView/blt202204190031","retrieved":1650352687893,"image":"https://www.bloter.net/data/blt/image/2022/04/19/blt202204190016.290x163.0.jpg"},{"title":"알뜰폰도 인터넷 결합하면 할인된다…LG유플러스·모요 손잡은 이유","contents":"<span class=\"writer\">이건한</span>                        <span class=\"date\">2022-04-19 12:51:30</span>","link":"https://www.bloter.net/newsView/blt202204190024","retrieved":1650342860615,"image":"https://www.bloter.net/data/blt/image/2022/04/19/blt202204190009.290x163.0.jpg"},{"title":"상장 검토 '아이지에이웍스'...영업이익 3배 뛴 까닭","contents":"<span class=\"writer\">황금빛</span>                        <span class=\"date\">2022-04-19 10:59:05</span>","link":"https://www.bloter.net/newsView/blt202204190004","retrieved":1650338661110,"image":"https://www.bloter.net/data/blt/image/2022/04/19/blt202204190003.290x163.0.jpg"},{"title":"구글맵 '러시아 군 시설 재개방' 의혹…구글 \"검열조차 안 했다\"","contents":"<span class=\"writer\">최경미</span>                        <span class=\"date\">2022-04-19 10:48:10</span>","link":"https://www.bloter.net/newsView/blt202204190006","retrieved":1650338661116,"image":"https://www.bloter.net/data/blt/image/2022/04/19/blt202204190006.290x163.0.png"},{"title":"美 법원 \"웹 스크래핑은 합법\"…링크드인, 불복하나","contents":"<span class=\"writer\">최경미</span>                        <span class=\"date\">2022-04-19 09:26:41</span>","link":"https://www.bloter.net/newsView/blt202204190002","retrieved":1650331484883,"image":"https://www.bloter.net/data/blt/image/2022/04/19/blt202204190002.290x163.0.png"}]}