{"title":"블로터 ─ 테크","url":"https://www.bloter.net/section?id=sectionTech","favicon":"https://www.bloter.net/favicon.png","elements":[{"title":"현대차·LG유플러스에 AI 면접 솔루션 공급한 제네시스랩은 어떤 기업?","contents":"<span class=\"writer\">박현준</span>                        <span class=\"date\">2022-07-06 08:00:01</span>","link":"https://www.bloter.net/newsView/blt202207050019","retrieved":1657063092207,"image":"https://www.bloter.net/data/blt/image/2022/07/05/blt202207050052.620x344.0.png"},{"title":"“수학은 편견·한계를 이해하는 과정”…허준이 교수, 필즈상 수상 ‘쾌거’","contents":"<span class=\"writer\">정두용</span>                        <span class=\"date\">2022-07-05 18:23:11</span>","link":"https://www.bloter.net/newsView/blt202207050018","retrieved":1657016352713,"image":"https://www.bloter.net/data/blt/image/2022/07/05/blt202207050045.290x163.0.jpg"},{"title":"[엔씨, 변화를 말하다]④새 IP '프로젝트G'는 MMO+RTS?","contents":"<span class=\"writer\">채성오</span>                        <span class=\"date\">2022-07-05 17:40:50</span>","link":"https://www.bloter.net/newsView/blt202207050016","retrieved":1657012669111,"image":"https://www.bloter.net/data/blt/image/2022/07/05/blt202207050040.290x163.0.jpg"},{"title":"카카오, 모빌리티 매각 방식 바꾸면 '직원 반발' 줄어들까","contents":"<span class=\"writer\">최창원</span>                        <span class=\"date\">2022-07-05 17:21:17</span>","link":"https://www.bloter.net/newsView/blt202207050010","retrieved":1657009341202,"image":"https://www.bloter.net/data/blt/image/2022/07/05/blt202207050015.290x163.0.png"},{"title":"5G 주파수 균형 맞추고 본격 경쟁 앞둔 SKT·KT·LGU+…투자로 이어질까","contents":"<span class=\"writer\">박현준</span>                        <span class=\"date\">2022-07-05 17:17:54</span>","link":"https://www.bloter.net/newsView/blt202207050014","retrieved":1657009341211,"image":"https://www.bloter.net/data/blt/image/2022/07/05/blt202207050031.290x163.0.jpg"},{"title":"‘8월 발사’ 韓 첫 달 궤도선 ‘다누리’ 美 이송…누리호 다음 도전 시작","contents":"<span class=\"writer\">정두용</span>                        <span class=\"date\">2022-07-05 17:12:38</span>","link":"https://www.bloter.net/newsView/blt202207050013","retrieved":1657009341214,"image":"https://www.bloter.net/data/blt/image/2022/07/05/blt202207050025.290x163.0.jpg"},{"title":"KT \"AI 주택만으로 5000억원 수주 간다\"…5대 '스페이스 DX' 가동","contents":"<span class=\"writer\">이건한</span>                        <span class=\"date\">2022-07-05 17:11:28</span>","link":"https://www.bloter.net/newsView/blt202207050012","retrieved":1657009341218,"image":"https://www.bloter.net/data/blt/image/2022/07/05/blt202207050018.290x163.0.jpg"},{"title":"'딱딱한 제약' 인식 엎었다…'구독자 10만명' 유한양행 유튜브 흥행 비결은?","contents":"<span class=\"writer\">안치영</span>                        <span class=\"date\">2022-07-05 13:49:13</span>","link":"https://www.bloter.net/newsView/blt202207050006","retrieved":1656998592133,"image":"https://www.bloter.net/data/blt/image/2022/07/05/blt202207050008.290x163.0.jpg"},{"title":"쇼핑몰 성장 방정식은?…오픈·버티컬 마켓 '복수 입점'","contents":"<span class=\"writer\">안신혜</span>                        <span class=\"date\">2022-07-05 13:17:58</span>","link":"https://www.bloter.net/newsView/blt202207050008","retrieved":1656995792221,"image":"https://www.bloter.net/data/blt/image/2022/07/05/blt202207050012.290x163.0.jpg"},{"title":"점유율 하락 쏘카, 비용 부담에도 '편도 서비스' 선보인다","contents":"<span class=\"writer\">최창원</span>                        <span class=\"date\">2022-07-05 13:07:24</span>","link":"https://www.bloter.net/newsView/blt202207050005","retrieved":1656995792222,"image":"https://www.bloter.net/data/blt/image/2022/07/05/blt202207050005.290x163.0.jpg"},{"title":"크립토랩, 어떻게 '스톤브릿지·알토스·키움인베' 눈에 들었나","contents":"<span class=\"writer\">최창원</span>                        <span class=\"date\">2022-07-05 13:06:51</span>","link":"https://www.bloter.net/newsView/blt202207050007","retrieved":1656995792224,"image":"https://www.bloter.net/data/blt/image/2022/07/05/blt202207050010.290x163.0.png"},{"title":"아마존, OTT 프라임 비디오 ‘워치파티’ 호환 채널 확장","contents":"<span class=\"writer\">정두용</span>                        <span class=\"date\">2022-07-05 11:19:36</span>","link":"https://www.bloter.net/newsView/blt202207050004","retrieved":1656992634160,"image":"https://www.bloter.net/data/blt/image/2022/07/05/blt202207050004.290x163.0.png"},{"title":"4조9000억원 현금 보유한 삼성SDS, 올해 첫 투자처로 왜 물류 택했나","contents":"<span class=\"writer\">박현준</span>                        <span class=\"date\">2022-07-05 10:53:40</span>","link":"https://www.bloter.net/newsView/blt202207050003","retrieved":1656992634160,"image":"https://www.bloter.net/data/blt/image/2022/07/05/blt202207050003.290x163.0.png"},{"title":"퓨처플레이, '초기 투자 심사역'도 육성한다","contents":"<span class=\"writer\">최창원</span>                        <span class=\"date\">2022-07-05 10:27:21</span>","link":"https://www.bloter.net/newsView/blt202207050002","retrieved":1656992634162,"image":"https://www.bloter.net/data/blt/image/2022/07/05/blt202207050002.290x163.0.png"},{"title":"[열쇳말]'5G FWA' 해외는 주목, 국내선 찬밥…왜?","contents":"<span class=\"writer\">이건한</span>                        <span class=\"date\">2022-07-05 06:00:02</span>","link":"https://www.bloter.net/newsView/blt202207040015","retrieved":1656969302274,"image":"https://www.bloter.net/data/blt/image/2022/07/04/blt202207040031.290x163.0.jpg"},{"title":"논란의 5G 주파수 추가 할당, 결국 LG유플러스 '단독 입찰'","contents":"<span class=\"writer\">이건한</span>                        <span class=\"date\">2022-07-04 18:44:06</span>","link":"https://www.bloter.net/newsView/blt202207040005","retrieved":1656930027641,"image":"https://www.bloter.net/data/blt/image/2022/07/04/blt202207040006.290x163.0.jpg"},{"title":"누리호 성공이 만든 효과…카이스트·서울대 큐브위성 ‘양방향 교신’","contents":"<span class=\"writer\">정두용</span>                        <span class=\"date\">2022-07-04 17:15:02</span>","link":"https://www.bloter.net/newsView/blt202207040011","retrieved":1656922935969,"image":"https://www.bloter.net/data/blt/image/2022/07/04/blt202207040018.290x163.0.jpg"},{"title":"'통신장비 강자' 시스코가 '스마트항만'에 꽂힌 이유","contents":"<span class=\"writer\">박현준</span>                        <span class=\"date\">2022-07-04 17:14:01</span>","link":"https://www.bloter.net/newsView/blt202207040013","retrieved":1656922935971,"image":"https://www.bloter.net/data/blt/image/2022/07/04/blt202207040027.290x163.0.png"}]}