{"title":"블로터 ─ 테크","url":"https://www.bloter.net/section?id=sectionTech","favicon":"https://www.bloter.net/favicon.png","elements":[{"title":"직접 계산하는 'DSR 계산기' 버려도 된다…핀다는 '알아서 계산'","contents":"<span class=\"writer\">강승혁</span>                        <span class=\"date\">2022-04-28 11:32:42</span>","link":"https://www.bloter.net/newsView/blt202204280032","retrieved":1651119098057,"image":"https://www.bloter.net/data/blt/image/2022/04/28/blt202204280006.620x344.0.jpg"},{"title":"[오~컬쳐]컴투스그룹·위메이드·Z홀딩스, 日 '더블점프 도쿄' 투자 이유는","contents":"<span class=\"writer\">채성오</span>                        <span class=\"date\">2022-04-28 11:14:01</span>","link":"https://www.bloter.net/newsView/blt202204280029","retrieved":1651119098071,"image":"https://www.bloter.net/data/blt/image/2022/04/28/blt202204280004.290x163.0.jpg"},{"title":"메타, 1분기 사용자 수 다시 증가…매출은 예상 밑돌아","contents":"<span class=\"writer\">최경미</span>                        <span class=\"date\">2022-04-28 09:43:39</span>","link":"https://www.bloter.net/newsView/blt202204280015","retrieved":1651110941885,"image":"https://www.bloter.net/data/blt/image/2022/04/28/blt202204280003.290x163.0.jpg"},{"title":"‘코로나 허위정보 온상’ 비판받던 스포티파이, 1분기 구독자 수 15% 증가","contents":"<span class=\"writer\">최경미</span>                        <span class=\"date\">2022-04-28 08:44:23</span>","link":"https://www.bloter.net/newsView/blt202204280007","retrieved":1651110941885,"image":"https://www.bloter.net/data/blt/image/2022/04/28/blt202204280002.290x163.0.jpeg"},{"title":"아이폰 '셀프 수리' 가능해졌다...애플, 미국 내 부품 판매 개시","contents":"<span class=\"writer\">최경미</span>                        <span class=\"date\">2022-04-28 08:06:33</span>","link":"https://www.bloter.net/newsView/blt202204280001","retrieved":1651101554179,"image":"https://www.bloter.net/data/blt/image/2022/04/28/blt202204280001.290x163.0.png"},{"title":"‘분기 최대 실적’ 삼성바이오로직스, 상승세 이어갈까","contents":"<span class=\"writer\">정두용</span>                        <span class=\"date\">2022-04-27 18:50:41</span>","link":"https://www.bloter.net/newsView/blt202204270168","retrieved":1651054837909,"image":"https://www.bloter.net/data/blt/image/2022/04/27/blt202204270044.290x163.0.jpg"},{"title":"LG이노텍, '10%대 영업이익률' 회복 나선다","contents":"<span class=\"writer\">최창원</span>                        <span class=\"date\">2022-04-27 18:37:46</span>","link":"https://www.bloter.net/newsView/blt202204270165","retrieved":1651054837909,"image":"https://www.bloter.net/data/blt/image/2022/04/27/blt202204270040.290x163.0.png"},{"title":"'글로벌'에 사활건 네이버, 웹툰에 4000억원 쏟는다","contents":"<span class=\"writer\">박현준</span>                        <span class=\"date\">2022-04-27 18:24:45</span>","link":"https://www.bloter.net/newsView/blt202204270164","retrieved":1651054837919,"image":"https://www.bloter.net/data/blt/image/2022/04/27/blt202204270036.290x163.0.png"},{"title":"[구하다, 기술을 말하다]②블록체인 플랫폼 '블링크'로 사업 영역 확장","contents":"<span class=\"writer\">안신혜</span>                        <span class=\"date\">2022-04-27 18:23:24</span>","link":"https://www.bloter.net/newsView/blt202204250040","retrieved":1651054837923,"image":"https://www.bloter.net/data/blt/image/2022/04/25/blt202204250026.290x163.0.jpg"},{"title":"삼성전기, 외형 성장 속 '현금흐름' 절반 급감","contents":"<span class=\"writer\">최창원</span>                        <span class=\"date\">2022-04-27 17:57:09</span>","link":"https://www.bloter.net/newsView/blt202204270158","retrieved":1651051160693,"image":"https://www.bloter.net/data/blt/image/2022/04/27/blt202204270030.290x163.0.png"},{"title":"LGD, 삼성전자 패널 납품 확정설 부인...“서로 니즈 맞아야”","contents":"<span class=\"writer\">이일호</span>                        <span class=\"date\">2022-04-27 17:54:16</span>","link":"https://www.bloter.net/newsView/blt202204270161","retrieved":1651051160693,"image":"https://www.bloter.net/data/blt/image/2022/04/27/blt202204270031.290x163.0.jpg"},{"title":"‘영업이익률 0.6%’ LG디스플레이, LCD 포트폴리오 재편 나선다","contents":"<span class=\"writer\">이일호</span>                        <span class=\"date\">2022-04-27 17:23:20</span>","link":"https://www.bloter.net/newsView/blt202204270147","retrieved":1651051160698,"image":"https://www.bloter.net/data/blt/image/2022/04/27/blt202204270024.290x163.0.jpg"},{"title":"삼성과 다른 셀트리온 협상력?…애브비와 소송 없이 시밀러 ‘특허 합의’","contents":"<span class=\"writer\">정두용</span>                        <span class=\"date\">2022-04-27 17:08:53</span>","link":"https://www.bloter.net/newsView/blt202204270089","retrieved":1651047700279,"image":"https://www.bloter.net/data/blt/image/2022/04/27/blt202204270023.290x163.0.jpg"},{"title":"AI 스피커와 대화하는 어르신들…KT가 '디지털 돌봄'에 주목한 이유","contents":"<span class=\"writer\">이건한</span>                        <span class=\"date\">2022-04-27 16:05:17</span>","link":"https://www.bloter.net/newsView/blt202204270042","retrieved":1651043856174,"image":"https://www.bloter.net/data/blt/image/2022/04/27/blt202204270020.290x163.0.jpg"},{"title":"230억원 투자받은 뉴빌리티, 올해 자체 로봇 배달 앱 낸다","contents":"<span class=\"writer\">황금빛</span>                        <span class=\"date\">2022-04-27 11:57:53</span>","link":"https://www.bloter.net/newsView/blt202204270008","retrieved":1651031011962,"image":"https://www.bloter.net/data/blt/image/2022/04/27/blt202204270005.290x163.0.jpg"},{"title":"넥슨, 격투·레이싱·루트슈터 신작 예열…글로벌 콘솔시장 정조준","contents":"<span class=\"writer\">채성오</span>                        <span class=\"date\">2022-04-27 11:30:55</span>","link":"https://www.bloter.net/newsView/blt202204270018","retrieved":1651031011966,"image":"https://www.bloter.net/data/blt/image/2022/04/27/blt202204270010.290x163.0.jpg"},{"title":"잘 팔리는 SK하이닉스, 고민거리는 '장비 리드타임'","contents":"<span class=\"writer\">최창원</span>                        <span class=\"date\">2022-04-27 11:30:22</span>","link":"https://www.bloter.net/newsView/blt202204270019","retrieved":1651031011968,"image":"https://www.bloter.net/data/blt/image/2022/04/27/blt202204270014.290x163.0.png"},{"title":"SK하이닉스, 판관비 1조 증가...품질 저하 D램 '충당금' 반영","contents":"<span class=\"writer\">최창원</span>                        <span class=\"date\">2022-04-27 10:57:03</span>","link":"https://www.bloter.net/newsView/blt202204270014","retrieved":1651031011969,"image":"https://www.bloter.net/data/blt/image/2022/04/27/blt202204270006.290x163.0.png"}]}